tresto/__init__.py
tresto/__main__.py
tresto/cli.py
tresto/config.py
tresto/py.typed
tresto/ai/__init__.py
tresto/ai/agent/__init__.py
tresto/ai/agent/agent.py
tresto/ai/agent/graph.py
tresto/ai/agent/state/__init__.py
tresto/ai/agent/tools/__init__.py
tresto/ai/agent/tools/ask_user.py
tresto/ai/agent/tools/deside_next_action.py
tresto/ai/agent/tools/generate.py
tresto/ai/agent/tools/list_directory.py
tresto/ai/agent/tools/playwright_codegen.py
tresto/ai/agent/tools/read_file_content.py
tresto/ai/agent/tools/run_test.py
tresto/ai/agent/tools/screenshot.py
tresto/ai/agent/tools/inspect/__init__.py
tresto/ai/agent/tools/inspect/recording.py
tresto/ai/agent/tools/inspect/tools/__init__.py
tresto/ai/agent/tools/inspect/tools/attrs.py
tresto/ai/agent/tools/inspect/tools/core.py
tresto/ai/agent/tools/inspect/tools/expand.py
tresto/ai/agent/tools/inspect/tools/logs.py
tresto/ai/agent/tools/inspect/tools/screenshot.py
tresto/ai/agent/tools/inspect/tools/show.py
tresto/ai/agent/tools/inspect/tools/stats.py
tresto/ai/agent/tools/inspect/tools/text.py
tresto/ai/agent/tools/project_inspect/__init__.py
tresto/ai/agent/tools/project_inspect/execution.py
tresto/ai/agent/tools/project_inspect/generation.py
tresto/ai/agent/tools/project_inspect/models.py
tresto/ai/connectors/__init__.py
tresto/ai/connectors/base.py
tresto/ai/connectors/factory.py
tresto/ai/connectors/anthropic/__init__.py
tresto/ai/connectors/anthropic/connector.py
tresto/ai/connectors/anthropic/settings.py
tresto/ai/connectors/openai/__init__.py
tresto/ai/connectors/openai/connector.py
tresto/ai/connectors/openai/settings.py
tresto/ai/models/rich_formattable.py
tresto/ai/prompts/__init__.py
tresto/ai/prompts/codegen.md
tresto/ai/prompts/create_test.md
tresto/ai/prompts/system.md
tresto/commands/__init__.py
tresto/commands/db.py
tresto/commands/hello.py
tresto/commands/init.py
tresto/commands/record.py
tresto/commands/version.py
tresto/commands/models/__init__.py
tresto/commands/models/list.py
tresto_ai-0.3.1.dist-info/METADATA
tresto_ai-0.3.1.dist-info/WHEEL
tresto_ai-0.3.1.dist-info/entry_points.txt
tresto_ai-0.3.1.dist-info/licenses/LICENSE
tresto_ai-0.3.1.dist-info/RECORD
