Metadata-Version: 2.4
Name: tresto-ai
Version: 0.3.1
Summary: AI-powered E2E testing CLI inspired by Playwright codegen
Project-URL: Homepage, https://github.com/LeaveMyYard/Tresto
Project-URL: Documentation, https://github.com/LeaveMyYard/Tresto#readme
Project-URL: Repository, https://github.com/LeaveMyYard/Tresto
Project-URL: Bug Tracker, https://github.com/LeaveMyYard/Tresto/issues
Author-email: LeaveMyYard <zhukovpavel2001@gmail.com>
License-Expression: MIT
License-File: LICENSE
Keywords: ai,automation,e2e,playwright,testing
Classifier: Development Status :: 3 - Alpha
Classifier: Intended Audience :: Developers
Classifier: License :: OSI Approved :: MIT License
Classifier: Programming Language :: Python :: 3
Classifier: Programming Language :: Python :: 3.9
Classifier: Programming Language :: Python :: 3.10
Classifier: Programming Language :: Python :: 3.11
Classifier: Programming Language :: Python :: 3.12
Classifier: Programming Language :: Python :: 3.13
Classifier: Topic :: Software Development :: Quality Assurance
Classifier: Topic :: Software Development :: Testing
Requires-Python: >=3.13
Requires-Dist: anthropic>=0.25.0
Requires-Dist: beautifulsoup4>=4.12.0
Requires-Dist: langchain-anthropic>=0.1.0
Requires-Dist: langchain-core>=0.1.0
Requires-Dist: langchain-openai>=0.1.0
Requires-Dist: langchain>=0.1.0
Requires-Dist: langgraph>=0.6.4
Requires-Dist: pathspec>=0.11.0
Requires-Dist: pillow>=11.3.0
Requires-Dist: playwright>=1.40.0
Requires-Dist: pydantic-settings>=2.10.1
Requires-Dist: pydantic>=2.0.0
Requires-Dist: pytest-asyncio>=1.1.0
Requires-Dist: pytest>=8.4.1
Requires-Dist: rich>=13.0.0
Requires-Dist: toml>=0.10.2
Requires-Dist: typer[all]>=0.9.0
Provides-Extra: dev
Requires-Dist: mypy>=1.0.0; extra == 'dev'
Requires-Dist: pre-commit>=3.0.0; extra == 'dev'
Requires-Dist: pytest-asyncio>=0.21.0; extra == 'dev'
Requires-Dist: pytest>=7.0.0; extra == 'dev'
Requires-Dist: ruff>=0.1.0; extra == 'dev'
